common/__init__.py
common/constants/__init__.py
common/constants/database_config.py
common/constants/level_dict.py
common/entity/__init__.py
common/entity/document.py
common/entity/relation_key.py
common/entity/timeline.py
common/service/__init__.py
common/service/iccc3.py
common/service/medical_text.py
common/service/multi_thread.py
common/tests/__init__.py
common/tests/test_date_util.py
common/tests/test_encrypt_util.py
common/tests/test_iccc3.py
common/tests/test_id_card_util.py
common/tests/test_list_util.py
common/tests/test_medical_text.py
common/tests/test_phone_util.py
common/tests/test_relation_key.py
common/tests/test_sql_util.py
common/tests/test_string_util.py
common/util/__init__.py
common/util/csv_util.py
common/util/database_connection_util.py
common/util/date_util.py
common/util/encrypt_util.py
common/util/excel_util.py
common/util/http_util.py
common/util/id_card_util.py
common/util/linux_util.py
common/util/list_util.py
common/util/phone_util.py
common/util/sql_util.py
common/util/string_util.py
common/util/timer_util.py
common/util/zip_util.py
ncpcs_common-5.0.0.dist-info/METADATA
ncpcs_common-5.0.0.dist-info/WHEEL
ncpcs_common-5.0.0.dist-info/top_level.txt
ncpcs_common-5.0.0.dist-info/RECORD
