Metadata-Version: 2.1
Name: ncpcs-common
Version: 5.0.0
Summary: UNKNOWN
Home-page: UNKNOWN
License: UNKNOWN
Platform: UNKNOWN
Requires-Dist: pytest
Requires-Dist: pymysql
Requires-Dist: python-dateutil
Requires-Dist: cryptography
